odoo/addons/currency_rate_update_oxr/README.rst
odoo/addons/currency_rate_update_oxr/__init__.py
odoo/addons/currency_rate_update_oxr/__manifest__.py
odoo/addons/currency_rate_update_oxr/i18n/currency_rate_update_oxr.pot
odoo/addons/currency_rate_update_oxr/models/__init__.py
odoo/addons/currency_rate_update_oxr/models/res_company.py
odoo/addons/currency_rate_update_oxr/models/res_config_settings.py
odoo/addons/currency_rate_update_oxr/models/res_currency_rate_provider_OXR.py
odoo/addons/currency_rate_update_oxr/readme/CONFIGURE.rst
odoo/addons/currency_rate_update_oxr/readme/CONTRIBUTORS.rst
odoo/addons/currency_rate_update_oxr/readme/DESCRIPTION.rst
odoo/addons/currency_rate_update_oxr/static/description/icon.png
odoo/addons/currency_rate_update_oxr/static/description/index.html
odoo/addons/currency_rate_update_oxr/tests/__init__.py
odoo/addons/currency_rate_update_oxr/tests/test_currency_rate_update_oxr.py
odoo/addons/currency_rate_update_oxr/views/res_config_settings.xml
odoo12_addon_currency_rate_update_oxr-12.0.1.0.2.dist-info/METADATA
odoo12_addon_currency_rate_update_oxr-12.0.1.0.2.dist-info/WHEEL
odoo12_addon_currency_rate_update_oxr-12.0.1.0.2.dist-info/top_level.txt
odoo12_addon_currency_rate_update_oxr-12.0.1.0.2.dist-info/RECORD
